fb_tools/__init__.py
fb_tools/app.py
fb_tools/argparse_actions.py
fb_tools/cfg_app.py
fb_tools/colcts.py
fb_tools/collections.py
fb_tools/common.py
fb_tools/config.py
fb_tools/errors.py
fb_tools/get_file_rm_app.py
fb_tools/handling_obj.py
fb_tools/local_version.py
fb_tools/mailaddress.py
fb_tools/merge.py
fb_tools/obj.py
fb_tools/pidfile.py
fb_tools/show_spinner_app.py
fb_tools/spinner.py
fb_tools/xlate.py
fb_tools/ddns/__init__.py
fb_tools/ddns/config.py
fb_tools/ddns/errors.py
fb_tools/ddns/myip_app.py
fb_tools/ddns/update_app.py
fb_tools/handler/__init__.py
fb_tools/handler/lock.py
fb_tools/multi_config/__init__.py
fb_tools/multi_config/files.py
fb_tools/multi_config/inits.py
fb_tools/multi_config/read.py
fb_tools/socket_obj/__init__.py
fb_tools/socket_obj/tcp.py
fb_tools/socket_obj/unix.py
fb_tools-2.8.1.data/data/share/locale/de/LC_MESSAGES/fb_tools.mo
fb_tools-2.8.1.data/data/share/locale/en/LC_MESSAGES/fb_tools.mo
fb_tools-2.8.1.data/scripts/get-file-to-remove
fb_tools-2.8.1.data/scripts/myip
fb_tools-2.8.1.data/scripts/show-spinner
fb_tools-2.8.1.data/scripts/update-ddns
fb_tools-2.8.1.dist-info/licenses/LICENSE
fb_tools-2.8.1.dist-info/METADATA
fb_tools-2.8.1.dist-info/WHEEL
fb_tools-2.8.1.dist-info/top_level.txt
fb_tools-2.8.1.dist-info/RECORD
