Metadata-Version: 2.4
Name: fb_tools
Version: 2.8.1
Summary: Modules for common used objects, error classes and methods.
Home-page: https://github.com/fbrehm/python_fb_tools
Author: Frank Brehm
Author-email: frank@brehm-online.com
License: LGPL3+
Platform: posix
Classifier: Development Status :: 4 - Beta
Classifier: Environment :: Console
Classifier: Intended Audience :: Developers
Classifier: License :: OSI Approved :: GNU Lesser General Public License v3 or later (LGPLv3+)
Classifier: Natural Language :: English
Classifier: Operating System :: POSIX
Classifier: Programming Language :: Python :: 3.6
Classifier: Programming Language :: Python :: 3.7
Classifier: Programming Language :: Python :: 3.8
Classifier: Programming Language :: Python :: 3.9
Classifier: Programming Language :: Python :: 3.10
Classifier: Programming Language :: Python :: 3.11
Classifier: Programming Language :: Python :: 3.12
Classifier: Topic :: Software Development :: Libraries :: Python Modules
Requires: argparse
Requires: six
Requires: fb_logging
Requires: packaging
Requires: requests
Requires: pytz
Requires: setuptools
Requires: wheel
Requires: Babel
Requires: PyYAML
Requires: toml
Requires: hjson
Requires: chardet
Requires: requests_mock
Provides: fb_tools
License-File: LICENSE
Requires-Dist: fb_logging
Requires-Dist: packaging
Requires-Dist: six
Requires-Dist: pytz
Requires-Dist: requests
Requires-Dist: Babel
Requires-Dist: chardet
Dynamic: description
Dynamic: license-file
Dynamic: provides
Dynamic: requires
